{"0":{"barri":"el Raval","titulats":27.2,"aturats":3.074,"renda_familiar":71.2,"over_65":31.9,"index_sobreenvelliment":50.7},"1":{"barri":"el Barri Gòtic","titulats":32.7,"aturats":892.0,"renda_familiar":106.1,"over_65":30.2,"index_sobreenvelliment":50.2},"2":{"barri":"la Barceloneta","titulats":30.6,"aturats":978.0,"renda_familiar":79.6,"over_65":null,"index_sobreenvelliment":58.1},"3":{"barri":"Sant Pere, Santa Caterina i la Ribera","titulats":42.1,"aturats":1.346,"renda_familiar":99.4,"over_65":33.6,"index_sobreenvelliment":53.2},"4":{"barri":"el Fort Pienc","titulats":40.4,"aturats":1.156,"renda_familiar":106.5,"over_65":25.3,"index_sobreenvelliment":52.3},"5":{"barri":"la Sagrada Família","titulats":39.5,"aturats":1.917,"renda_familiar":101.8,"over_65":27.5,"index_sobreenvelliment":53.5},"6":{"barri":"la Dreta de l'Eixample","titulats":52.8,"aturats":1.255,"renda_familiar":175.9,"over_65":27.1,"index_sobreenvelliment":54.0},"7":{"barri":"l'Antiga Esquerra de l'Eixample","titulats":49.7,"aturats":1.345,"renda_familiar":137.2,"over_65":29.0,"index_sobreenvelliment":54.4},"8":{"barri":"la Nova Esquerra de l'Eixample","titulats":44.9,"aturats":2.117,"renda_familiar":110.2,"over_65":26.8,"index_sobreenvelliment":51.6},"9":{"barri":"Sant Antoni","titulats":38.9,"aturats":1.535,"renda_familiar":104.2,"over_65":28.5,"index_sobreenvelliment":56.4},"10":{"barri":"el Poble-sec","titulats":29.6,"aturats":2.045,"renda_familiar":82.2,"over_65":28.6,"index_sobreenvelliment":53.7},"11":{"barri":"la Marina del Prat Vermell","titulats":7.8,"aturats":93.0,"renda_familiar":40.0,"over_65":31.5,"index_sobreenvelliment":53.2},"12":{"barri":"la Marina de Port","titulats":null,"aturats":1.548,"renda_familiar":69.3,"over_65":25.4,"index_sobreenvelliment":53.8},"13":{"barri":"la Font de la Guatlla","titulats":31.9,"aturats":516.0,"renda_familiar":82.9,"over_65":24.9,"index_sobreenvelliment":51.9},"14":{"barri":"Hostafrancs","titulats":33.6,"aturats":684.0,"renda_familiar":99.0,"over_65":24.7,"index_sobreenvelliment":48.9},"15":{"barri":"la Bordeta","titulats":null,"aturats":null,"renda_familiar":null,"over_65":null,"index_sobreenvelliment":null},"16":{"barri":"Sants - Badal","titulats":28.2,"aturats":845.0,"renda_familiar":81.0,"over_65":23.7,"index_sobreenvelliment":49.3},"17":{"barri":"Sants","titulats":33.5,"aturats":1.629,"renda_familiar":99.0,"over_65":26.9,"index_sobreenvelliment":53.4},"18":{"barri":"les Corts","titulats":null,"aturats":1.665,"renda_familiar":120.0,"over_65":23.7,"index_sobreenvelliment":50.1},"19":{"barri":"la Maternitat i Sant Ramon","titulats":40.4,"aturats":835.0,"renda_familiar":114.2,"over_65":22.8,"index_sobreenvelliment":51.0},"20":{"barri":"Pedralbes","titulats":52.6,"aturats":208.0,"renda_familiar":248.8,"over_65":20.8,"index_sobreenvelliment":55.7},"21":{"barri":"Vallvidrera, el Tibidabo i les Planes","titulats":null,"aturats":null,"renda_familiar":null,"over_65":null,"index_sobreenvelliment":null},"22":{"barri":"Sarrià","titulats":null,"aturats":null,"renda_familiar":null,"over_65":null,"index_sobreenvelliment":null},"23":{"barri":"les Tres Torres","titulats":null,"aturats":null,"renda_familiar":null,"over_65":null,"index_sobreenvelliment":null},"24":{"barri":"Sant Gervasi - la Bonanova","titulats":null,"aturats":null,"renda_familiar":null,"over_65":null,"index_sobreenvelliment":null},"25":{"barri":"Sant Gervasi - Galvany","titulats":null,"aturats":null,"renda_familiar":null,"over_65":null,"index_sobreenvelliment":null},"26":{"barri":"el Putxet i el Farró","titulats":null,"aturats":null,"renda_familiar":null,"over_65":null,"index_sobreenvelliment":null},"27":{"barri":"Vallcarca i els Penitents","titulats":42.0,"aturats":615.0,"renda_familiar":112.5,"over_65":25.8,"index_sobreenvelliment":54.1},"28":{"barri":"el Coll","titulats":32.3,"aturats":259.0,"renda_familiar":87.0,"over_65":26.3,"index_sobreenvelliment":51.7},"29":{"barri":"la Salut","titulats":42.1,"aturats":526.0,"renda_familiar":109.9,"over_65":25.4,"index_sobreenvelliment":51.1},"30":{"barri":"la Vila de Gràcia","titulats":47.5,"aturats":1.939,"renda_familiar":104.4,"over_65":30.8,"index_sobreenvelliment":55.1},"31":{"barri":"el Camp d'en Grassot i Gràcia Nova","titulats":null,"aturats":1.277,"renda_familiar":105.7,"over_65":27.0,"index_sobreenvelliment":51.4},"32":{"barri":"el Baix Guinardó","titulats":34.3,"aturats":990.0,"renda_familiar":92.0,"over_65":24.9,"index_sobreenvelliment":58.3},"33":{"barri":"Can Baró","titulats":29.8,"aturats":377.0,"renda_familiar":83.3,"over_65":25.5,"index_sobreenvelliment":52.5},"34":{"barri":"el Guinardó","titulats":32.0,"aturats":1.475,"renda_familiar":79.1,"over_65":26.3,"index_sobreenvelliment":53.5},"35":{"barri":"la Font d'en Fargues","titulats":33.6,"aturats":464.0,"renda_familiar":92.5,"over_65":20.1,"index_sobreenvelliment":49.3},"36":{"barri":"el Carmel","titulats":14.8,"aturats":1.586,"renda_familiar":54.2,"over_65":23.7,"index_sobreenvelliment":53.2},"37":{"barri":"la Teixonera","titulats":18.4,"aturats":489.0,"renda_familiar":73.7,"over_65":23.3,"index_sobreenvelliment":53.9},"38":{"barri":"Sant Genís dels Agudells","titulats":21.3,"aturats":297.0,"renda_familiar":84.1,"over_65":25.7,"index_sobreenvelliment":62.8},"39":{"barri":"Montbau","titulats":27.9,"aturats":215.0,"renda_familiar":79.8,"over_65":27.2,"index_sobreenvelliment":73.4},"40":{"barri":"la Vall d'Hebron","titulats":31.1,"aturats":229.0,"renda_familiar":95.8,"over_65":24.1,"index_sobreenvelliment":56.0},"41":{"barri":"la Clota","titulats":29.3,"aturats":16.0,"renda_familiar":93.5,"over_65":32.6,"index_sobreenvelliment":65.1},"42":{"barri":"Horta","titulats":24.5,"aturats":1.315,"renda_familiar":79.8,"over_65":23.0,"index_sobreenvelliment":57.0},"43":{"barri":"Vilapicina i la Torre Llobeta","titulats":23.9,"aturats":1.22,"renda_familiar":63.8,"over_65":26.0,"index_sobreenvelliment":54.8},"44":{"barri":"Porta","titulats":18.1,"aturats":1.199,"renda_familiar":64.4,"over_65":25.1,"index_sobreenvelliment":57.9},"45":{"barri":"el Turó de la Peira","titulats":16.5,"aturats":758.0,"renda_familiar":51.9,"over_65":31.8,"index_sobreenvelliment":67.6},"46":{"barri":"Can Peguera","titulats":null,"aturats":null,"renda_familiar":null,"over_65":null,"index_sobreenvelliment":null},"47":{"barri":"la Guineueta","titulats":19.0,"aturats":857.0,"renda_familiar":53.8,"over_65":24.5,"index_sobreenvelliment":57.3},"48":{"barri":"Canyelles","titulats":13.2,"aturats":418.0,"renda_familiar":52.2,"over_65":21.3,"index_sobreenvelliment":45.8},"49":{"barri":"les Roquetes","titulats":9.8,"aturats":906.0,"renda_familiar":49.7,"over_65":23.4,"index_sobreenvelliment":50.4},"50":{"barri":"Verdun","titulats":12.9,"aturats":695.0,"renda_familiar":51.3,"over_65":28.2,"index_sobreenvelliment":58.0},"51":{"barri":"la Prosperitat","titulats":13.2,"aturats":1.347,"renda_familiar":56.0,"over_65":25.6,"index_sobreenvelliment":58.0},"52":{"barri":"la Trinitat Nova","titulats":9.6,"aturats":620.0,"renda_familiar":48.2,"over_65":31.4,"index_sobreenvelliment":52.9},"53":{"barri":"Torre Baró","titulats":8.9,"aturats":172.0,"renda_familiar":46.5,"over_65":21.3,"index_sobreenvelliment":44.9},"54":{"barri":"Ciutat Meridiana","titulats":7.4,"aturats":896.0,"renda_familiar":38.6,"over_65":22.3,"index_sobreenvelliment":53.4},"55":{"barri":"Vallbona","titulats":9.5,"aturats":104.0,"renda_familiar":40.9,"over_65":13.9,"index_sobreenvelliment":59.4},"56":{"barri":"la Trinitat Vella","titulats":10.4,"aturats":831.0,"renda_familiar":47.1,"over_65":22.4,"index_sobreenvelliment":49.0},"57":{"barri":"Baró de Viver","titulats":7.1,"aturats":114.0,"renda_familiar":68.9,"over_65":28.0,"index_sobreenvelliment":52.3},"58":{"barri":"el Bon Pastor","titulats":14.3,"aturats":647.0,"renda_familiar":65.1,"over_65":22.7,"index_sobreenvelliment":52.7},"59":{"barri":"Sant Andreu","titulats":26.8,"aturats":2.62,"renda_familiar":77.7,"over_65":23.1,"index_sobreenvelliment":47.4},"60":{"barri":"la Sagrera","titulats":26.0,"aturats":1.17,"renda_familiar":77.1,"over_65":22.3,"index_sobreenvelliment":47.7},"61":{"barri":"el Congrés i els Indians","titulats":27.7,"aturats":570.0,"renda_familiar":75.1,"over_65":28.8,"index_sobreenvelliment":60.3},"62":{"barri":"Navas","titulats":28.0,"aturats":877.0,"renda_familiar":81.6,"over_65":26.2,"index_sobreenvelliment":53.3},"63":{"barri":"el Camp de l'Arpa del Clot","titulats":32.8,"aturats":1.71,"renda_familiar":81.7,"over_65":26.1,"index_sobreenvelliment":50.6},"64":{"barri":"el Clot","titulats":29.4,"aturats":1.169,"renda_familiar":83.6,"over_65":23.1,"index_sobreenvelliment":46.8},"65":{"barri":"el Parc i la Llacuna del Poblenou","titulats":37.1,"aturats":572.0,"renda_familiar":100.4,"over_65":26.1,"index_sobreenvelliment":48.4},"66":{"barri":"la Vila Olímpica del Poblenou","titulats":null,"aturats":null,"renda_familiar":null,"over_65":null,"index_sobreenvelliment":null},"67":{"barri":"el Poblenou","titulats":36.2,"aturats":1.339,"renda_familiar":99.9,"over_65":25.8,"index_sobreenvelliment":53.0},"68":{"barri":"Diagonal Mar i el Front Marítim del Poblenou","titulats":null,"aturats":null,"renda_familiar":null,"over_65":null,"index_sobreenvelliment":null},"69":{"barri":"el Besòs i el Maresme","titulats":12.8,"aturats":1.392,"renda_familiar":60.4,"over_65":26.4,"index_sobreenvelliment":54.8},"70":{"barri":"Provençals del Poblenou","titulats":26.9,"aturats":927.0,"renda_familiar":102.3,"over_65":22.8,"index_sobreenvelliment":49.9},"71":{"barri":"Sant Martí de Provençals","titulats":21.0,"aturats":1.29,"renda_familiar":67.4,"over_65":24.9,"index_sobreenvelliment":57.6},"72":{"barri":"la Verneda i la Pau","titulats":15.1,"aturats":1.461,"renda_familiar":57.0,"over_65":21.8,"index_sobreenvelliment":55.1}}